docker_compose_watch-0.0.1.dist-info/DESCRIPTION.rst
docker_compose_watch-0.0.1.dist-info/METADATA
docker_compose_watch-0.0.1.dist-info/RECORD
docker_compose_watch-0.0.1.dist-info/WHEEL
docker_compose_watch-0.0.1.dist-info/entry_points.txt
docker_compose_watch-0.0.1.dist-info/metadata.json
docker_compose_watch-0.0.1.dist-info/top_level.txt
dockercomposewatch/__init__.py
